{
  "db_name": "PostgreSQL",
  "query": "SELECT * FROM conversation",
  "describe": {
    "columns": [
      {
        "ordinal": 0,
        "name": "id",
        "type_info": "Uuid"
      },
      {
        "ordinal": 1,
        "name": "title",
        "type_info": "Text"
      },
      {
        "ordinal": 2,
        "name": "category",
        "type_info": "Text"
      },
      {
        "ordinal": 3,
        "name": "created_at",
        "type_info": "Timestamptz"
      },
      {
        "ordinal": 4,
        "name": "updated_at",
        "type_info": "Timestamptz"
      },
      {
        "ordinal": 5,
        "name": "user_id",
        "type_info": "Text"
      }
    ],
    "parameters": {
      "Left": []
    },
    "nullable": [
      false,
      true,
      false,
      false,
      false,
      false
    ]
  },
  "hash": "a21cbb539948a486cb8c160ad36857d3ab0ca9f40be5881799d280a8203ac111"
}
